nerdfont/__init__.py
nerdfont/generate.py
nerdfont/icons.py
nerdfont-3.4.0.post1.dist-info/METADATA
nerdfont-3.4.0.post1.dist-info/WHEEL
nerdfont-3.4.0.post1.dist-info/top_level.txt
nerdfont-3.4.0.post1.dist-info/RECORD
