Metadata-Version: 2.4
Name: nerdfont
Version: 3.4.0.post1
Summary: The Nerd Font icon set for python
Home-page: https://github.com/Larspolo/nerdfont-python
Author: Larspolo
Maintainer: Larspolo
License: Code: Apache License, Version 2.0, Icons: Nerd Fonts Licensing
Classifier: Environment :: Console
Classifier: Programming Language :: Python :: 3
Dynamic: author
Dynamic: classifier
Dynamic: description
Dynamic: description-content-type
Dynamic: home-page
Dynamic: license
Dynamic: maintainer
Dynamic: summary
